uw_itbill/__init__.py
uw_itbill/dao.py
uw_itbill/models.py
uw_itbill/provision.py
uw_itbill/subscription.py
uw_itbill/test.py
uw_itbill/util.py
UW_RestClients_ITBill-0.1.1.dist-info/LICENSE
UW_RestClients_ITBill-0.1.1.dist-info/METADATA
UW_RestClients_ITBill-0.1.1.dist-info/WHEEL
UW_RestClients_ITBill-0.1.1.dist-info/top_level.txt
UW_RestClients_ITBill-0.1.1.dist-info/RECORD
