Metadata-Version: 2.1
Name: UW-RestClients-ITBill
Version: 0.1.1
Summary: A library for connecting to UW IT-Bill API
Home-page: https://github.com/uw-it-aca/uw-restclients-itbill
Author: UW-IT T&LS
Author-email: aca-it@uw.edu
License: Apache License, Version 2.0
Classifier: Intended Audience :: Developers
Classifier: License :: OSI Approved :: Apache Software License
Classifier: Operating System :: OS Independent
Classifier: Programming Language :: Python
License-File: LICENSE
Requires-Dist: UW-RestClients-Core <2.0
Requires-Dist: mock
